Práctica/Guía 4/Verilog/tp4ej3/A/dec_to_bcd.v
module dec_to_bcd (
    input [9:0] dec,
    output reg [3:0] bcd
);
    

always @(*) begin

    case (dec)
        10'b0000000000: bcd = 4'b1111;
        10'b0000000001: bcd = 4'b0000; 
        10'b0000000010: bcd = 4'b0001; 
        10'b0000000100: bcd = 4'b0010; 
        10'b0000001000: bcd = 4'b0011; 
        10'b0000010000: bcd = 4'b0100; 
        10'b0000100000: bcd = 4'b0101; 
        10'b0001000000: bcd = 4'b0110; 
        10'b0010000000: bcd = 4'b0111; 
        10'b0100000000: bcd = 4'b1000;  
        10'b1000000000: bcd = 4'b1001;  
        default: bcd = 4'bxxxx;
    endcase

end
    
endmodule

Práctica/Guía 4/Verilog/tp4ej3/A/dec_to_bcd_tb.v
`define DUMPSTR(x) `"x.vcd`"
`timescale 100 ns / 10 ns

module dec_to_bcd_tb;

parameter DURATION = 10;
reg clk = 0;
always #0.5 clk = ~clk;

reg [9:0] test_dec;
wire [3:0] test_bcd;

// Instancia del módulo a probar
dec_to_bcd UUT (
    .dec(test_dec), 
    .bcd(test_bcd)
);

initial begin

    $dumpfile(`DUMPSTR(`VCD_OUTPUT));
    $dumpvars(0, dec_to_bcd_tb);

    #1 test_dec = 10'b0000000000;
    #1 test_dec = 10'b0000000001;
    #1 test_dec = 10'b0000000010;
    #1 test_dec = 10'b0000000100;
    #1 test_dec = 10'b0000001000;
    #1 test_dec = 10'b0000010000;
    #1 test_dec = 10'b0000100000;
    #1 test_dec = 10'b0001000000;
    #1 test_dec = 10'b0010000000;
    #1 test_dec = 10'b0100000000;
    #1 test_dec = 10'b1000000000;


    #(DURATION) $display("Fin de la simulación.");
    $finish; // Terminar la simulación
end

endmodule

Práctica/Guía 4/Verilog/tp4ej3/A/dec_to_bcd_tb.vcd
$date
	Tue Apr 16 14:07:34 2024
$end
$version
	Icarus Verilog
$end
$timescale
	1ps
$end
$scope module dec_to_bcd_tb $end
$var wire 4 ! test_bcd [3:0] $end
$var reg 1 " clk $end
$var reg 10 # test_dec [9:0] $end
$scope module UUT $end
$var wire 10 $ dec [9:0] $end
$var reg 4 % bcd [3:0] $end
$upscope $end
$upscope $end
$enddefinitions $end
#0
$dumpvars
bx %
bx $
bx #
0"
bx !
$end
#50000
1"
#100000
b1111 !
b1111 %
0"
b0 #
b0 $
#150000
1"
#200000
b0 !
b0 %
0"
b1 #
b1 $
#250000
1"
#300000
b1 !
b1 %
0"
b10 #
b10 $
#350000
1"
#400000
b10 !
b10 %
0"
b100 #
b100 $
#450000
1"
#500000
b11 !
b11 %
0"
b1000 #
b1000 $
#550000
1"
#600000
b100 !
b100 %
0"
b10000 #
b10000 $
#650000
1"
#700000
b101 !
b101 %
0"
b100000 #
b100000 $
#750000
1"
#800000
b110 !
b110 %
0"
b1000000 #
b1000000 $
#850000
1"
#900000
b111 !
b111 %
0"
b10000000 #
b10000000 $
#950000
1"
#1000000
b1000 !
b1000 %
0"
b100000000 #
b100000000 $
#1050000
1"
#1100000
b1001 !
b1001 %
0"
b1000000000 #
b1000000000 $
