Práctica/Guía 2/tp2ej4/A/CuatroA.v
module CuatroA (
    input wire a,
    input wire b,
    input wire c,
    input wire d,
    input wire e,
    input wire f,
    output wire x,
    output wire y
);
    
assign x = ~((a & ~b) | (~c & d) | (e & f));
assign y = (~a | b) & (c | ~d) & (~e | ~f);

endmodule

Práctica/Guía 2/tp2ej4/A/CuatroA_tb.v
`define DUMPSTR(x) `"x.vcd`"
`timescale 100 ns / 10 ns //Define la unidad de tiempo

module CuatroA_tb();
    
    parameter DURATION = 10;
    reg clk = 0;
    always #0.5 clk = ~clk;

    reg test_a, test_b, test_c, test_d, test_e, test_f;
    wire test_x, test_y;

    CuatroA UUT_CuatroA(
        .a(test_a),
        .b(test_b),
        .c(test_c),
        .d(test_d),
        .e(test_e),
        .f(test_f),
        .x(test_x),
        .y(test_y)
        
    );

    initial begin
        
        $dumpfile(`DUMPSTR(`VCD_OUTPUT));
        $dumpvars(0, CuatroA_tb);

        #1
        test_a = 0; test_b = 0; test_c = 0; test_d = 0; test_e = 0; test_f = 0;
        #1
        test_a = 0; test_b = 0; test_c = 0; test_d = 0; test_e = 0; test_f = 1;
        #1
        test_a = 0; test_b = 0; test_c = 0; test_d = 0; test_e = 1; test_f = 0;
        #1
        test_a = 0; test_b = 0; test_c = 0; test_d = 0; test_e = 1; test_f = 1;
        #1
        test_a = 0; test_b = 0; test_c = 0; test_d = 1; test_e = 0; test_f = 0;
        #1
        test_a = 0; test_b = 0; test_c = 0; test_d = 1; test_e = 0; test_f = 1;
        #1
        test_a = 0; test_b = 0; test_c = 0; test_d = 1; test_e = 1; test_f = 0;
        #1
        test_a = 0; test_b = 0; test_c = 0; test_d = 1; test_e = 1; test_f = 1;
        #1
        test_a = 0; test_b = 0; test_c = 1; test_d = 0; test_e = 0; test_f = 0;
        #1
        test_a = 0; test_b = 0; test_c = 1; test_d = 0; test_e = 0; test_f = 1;
        #1
        test_a = 0; test_b = 0; test_c = 1; test_d = 0; test_e = 1; test_f = 0;
        #1
        test_a = 0; test_b = 0; test_c = 1; test_d = 0; test_e = 1; test_f = 1;
        #1
        test_a = 0; test_b = 0; test_c = 1; test_d = 1; test_e = 0; test_f = 0;
        #1
        test_a = 0; test_b = 0; test_c = 1; test_d = 1; test_e = 0; test_f = 1;
        #1
        test_a = 0; test_b = 0; test_c = 1; test_d = 1; test_e = 1; test_f = 0;
        #1
        test_a = 0; test_b = 0; test_c = 1; test_d = 1; test_e = 1; test_f = 1;
        #1
        test_a = 0; test_b = 1; test_c = 0; test_d = 0; test_e = 0; test_f = 0;
        #1
        test_a = 0; test_b = 1; test_c = 0; test_d = 0; test_e = 0; test_f = 1;
        #1
        test_a = 0; test_b = 1; test_c = 0; test_d = 0; test_e = 1; test_f = 0;
        #1
        test_a = 0; test_b = 1; test_c = 0; test_d = 0; test_e = 1; test_f = 1;
        #1
        test_a = 0; test_b = 1; test_c = 0; test_d = 1; test_e = 0; test_f = 0;
        #1
        test_a = 0; test_b = 1; test_c = 0; test_d = 1; test_e = 0; test_f = 1;
        #1
        test_a = 0; test_b = 1; test_c = 0; test_d = 1; test_e = 1; test_f = 0;
        #1
        test_a = 0; test_b = 1; test_c = 0; test_d = 1; test_e = 1; test_f = 1;
        #1
        test_a = 0; test_b = 1; test_c = 1; test_d = 0; test_e = 0; test_f = 0;
        #1
        test_a = 0; test_b = 1; test_c = 1; test_d = 0; test_e = 0; test_f = 1;
        #1
        test_a = 0; test_b = 1; test_c = 1; test_d = 0; test_e = 1; test_f = 0;
        #1
        test_a = 0; test_b = 1; test_c = 1; test_d = 0; test_e = 1; test_f = 1;
        #1
        test_a = 0; test_b = 1; test_c = 1; test_d = 1; test_e = 0; test_f = 0;
        #1
        test_a = 0; test_b = 1; test_c = 1; test_d = 1; test_e = 0; test_f = 1;
        #1
        test_a = 0; test_b = 1; test_c = 1; test_d = 1; test_e = 1; test_f = 0;
        #1
        test_a = 0; test_b = 1; test_c = 1; test_d = 1; test_e = 1; test_f = 1;
        #1
        test_a = 1; test_b = 0; test_c = 0; test_d = 0; test_e = 0; test_f = 0;
        #1
        test_a = 1; test_b = 0; test_c = 0; test_d = 0; test_e = 0; test_f = 1;
        #1
        test_a = 1; test_b = 0; test_c = 0; test_d = 0; test_e = 1; test_f = 0;
        #1
        test_a = 1; test_b = 0; test_c = 0; test_d = 0; test_e = 1; test_f = 1;
        #1
        test_a = 1; test_b = 0; test_c = 0; test_d = 1; test_e = 0; test_f = 0;
        #1
        test_a = 1; test_b = 0; test_c = 0; test_d = 1; test_e = 0; test_f = 1;
        #1
        test_a = 1; test_b = 0; test_c = 0; test_d = 1; test_e = 1; test_f = 0;
        #1
        test_a = 1; test_b = 0; test_c = 0; test_d = 1; test_e = 1; test_f = 1;
        #1
        test_a = 1; test_b = 0; test_c = 1; test_d = 0; test_e = 0; test_f = 0;
        #1
        test_a = 1; test_b = 0; test_c = 1; test_d = 0; test_e = 0; test_f = 1;
        #1
        test_a = 1; test_b = 0; test_c = 1; test_d = 0; test_e = 1; test_f = 0;
        #1
        test_a = 1; test_b = 0; test_c = 1; test_d = 0; test_e = 1; test_f = 1;
        #1
        test_a = 1; test_b = 0; test_c = 1; test_d = 1; test_e = 0; test_f = 0;
        #1
        test_a = 1; test_b = 0; test_c = 1; test_d = 1; test_e = 0; test_f = 1;
        #1
        test_a = 1; test_b = 0; test_c = 1; test_d = 1; test_e = 1; test_f = 0;
        #1
        test_a = 1; test_b = 0; test_c = 1; test_d = 1; test_e = 1; test_f = 1;
        #1
        test_a = 1; test_b = 1; test_c = 0; test_d = 0; test_e = 0; test_f = 0;
        #1
        test_a = 1; test_b = 1; test_c = 0; test_d = 0; test_e = 0; test_f = 1;
        #1
        test_a = 1; test_b = 1; test_c = 0; test_d = 0; test_e = 1; test_f = 0;
        #1
        test_a = 1; test_b = 1; test_c = 0; test_d = 0; test_e = 1; test_f = 1;
        #1
        test_a = 1; test_b = 1; test_c = 0; test_d = 1; test_e = 0; test_f = 0;
        #1
        test_a = 1; test_b = 1; test_c = 0; test_d = 1; test_e = 0; test_f = 1;
        #1
        test_a = 1; test_b = 1; test_c = 0; test_d = 1; test_e = 1; test_f = 0;
        #1
        test_a = 1; test_b = 1; test_c = 0; test_d = 1; test_e = 1; test_f = 1;
        #1
        test_a = 1; test_b = 1; test_c = 1; test_d = 0; test_e = 0; test_f = 0;
        #1
        test_a = 1; test_b = 1; test_c = 1; test_d = 0; test_e = 0; test_f = 1;
        #1
        test_a = 1; test_b = 1; test_c = 1; test_d = 0; test_e = 1; test_f = 0;
        #1
        test_a = 1; test_b = 1; test_c = 1; test_d = 0; test_e = 1; test_f = 1;
        #1
        test_a = 1; test_b = 1; test_c = 1; test_d = 1; test_e = 0; test_f = 0;
        #1
        test_a = 1; test_b = 1; test_c = 1; test_d = 1; test_e = 0; test_f = 1;
        #1
        test_a = 1; test_b = 1; test_c = 1; test_d = 1; test_e = 1; test_f = 0;
        #1
        test_a = 1; test_b = 1; test_c = 1; test_d = 1; test_e = 1; test_f = 1;


        #(DURATION) $display("Fin de la simulación.");        
        $finish;

    end

endmodule

Práctica/tp2ej4/A/CuatroA_tb.vcd
$date
	Sat Apr 13 14:18:24 2024
$end
$version
	Icarus Verilog
$end
$timescale
	1ps
$end
$scope module CuatroA_tb $end
$var wire 1 ! test_y $end
$var wire 1 " test_x $end
$var parameter 32 # DURATION $end
$var reg 1 $ clk $end
$var reg 1 % test_a $end
$var reg 1 & test_b $end
$var reg 1 ' test_c $end
$var reg 1 ( test_d $end
$var reg 1 ) test_e $end
$var reg 1 * test_f $end
$scope module UUT_CuatroA $end
$var wire 1 % a $end
$var wire 1 & b $end
$var wire 1 ' c $end
$var wire 1 ( d $end
$var wire 1 ) e $end
$var wire 1 * f $end
$var wire 1 " x $end
$var wire 1 ! y $end
$upscope $end
$upscope $end
$enddefinitions $end
$comment Show the parameter values. $end
$dumpall
b1010 #
$end
#0
$dumpvars
x*
x)
x(
x'
x&
x%
0$
x"
x!
$end
#50000
1$
#100000
1"
1!
0$
0*
0)
0(
0'
0&
0%
#150000
1$
#200000
0$
1*
#250000
1$
#300000
0$
0*
1)
#350000
1$
#400000
0"
0!
0$
1*
#450000
1$
#500000
0$
0*
0)
1(
#550000
1$
#600000
0$
1*
#650000
1$
#700000
0$
0*
1)
#750000
1$
#800000
0$
1*
#850000
1$
#900000
1"
1!
0$
0*
0)
0(
1'
#950000
1$
#1000000
0$
1*
#1050000
1$
#1100000
0$
0*
1)
#1150000
1$
#1200000
0"
0!
0$
1*
#1250000
1$
#1300000
1"
1!
0$
0*
0)
1(
#1350000
1$
#1400000
0$
1*
#1450000
1$
#1500000
0$
0*
1)
#1550000
1$
#1600000
0"
0!
0$
1*
#1650000
1$
#1700000
1!
1"
0$
0*
0)
0(
0'
1&
#1750000
1$
#1800000
0$
1*
#1850000
1$
#1900000
0$
0*
1)
#1950000
1$
#2000000
0"
0!
0$
1*
#2050000
1$
#2100000
0$
0*
0)
1(
#2150000
1$
#2200000
0$
1*
#2250000
1$
#2300000
0$
0*
1)
#2350000
1$
#2400000
0$
1*
#2450000
1$
#2500000
1"
1!
0$
0*
0)
0(
1'
#2550000
1$
#2600000
0$
1*
#2650000
1$
#2700000
0$
0*
1)
#2750000
1$
#2800000
0"
0!
0$
1*
#2850000
1$
#2900000
1"
1!
0$
0*
0)
1(
#2950000
1$
#3000000
0$
1*
#3050000
1$
#3100000
0$
0*
1)
#3150000
1$
#3200000
0"
0!
0$
1*
#3250000
1$
#3300000
0"
0$
0*
0)
0(
0'
0&
1%
#3350000
1$
#3400000
0$
1*
#3450000
1$
#3500000
0$
0*
1)
#3550000
1$
#3600000
0$
1*
#3650000
1$
#3700000
0$
0*
0)
1(
#3750000
1$
#3800000
0$
1*
#3850000
1$
#3900000
0$
0*
1)
#3950000
1$
#4000000
0$
1*
#4050000
1$
#4100000
0$
0*
0)
0(
1'
#4150000
1$
#4200000
0$
1*
#4250000
1$
#4300000
0$
0*
1)
#4350000
1$
#4400000
0$
1*
#4450000
1$
#4500000
0$
0*
0)
1(
#4550000
1$
#4600000
0$
1*
#4650000
1$
#4700000
0$
0*
1)
#4750000
1$
#4800000
0$
1*
#4850000
1$
#4900000
1"
1!
0$
0*
0)
0(
0'
1&
#4950000
1$
#5000000
0$
1*
#5050000
1$
#5100000
0$
0*
1)
#5150000
1$
#5200000
0"
0!
0$
1*
#5250000
1$
#5300000
0$
0*
0)
1(
#5350000
1$
#5400000
0$
1*
#5450000
1$
#5500000
0$
0*
1)
#5550000
1$
#5600000
0$
1*
#5650000
1$
#5700000
1"
1!
0$
0*
0)
0(
1'
#5750000
1$
#5800000
0$
1*
#5850000
1$
#5900000
0$
0*
1)
#5950000
1$
#6000000
0"
0!
0$
1*
#6050000
1$
#6100000
1"
1!
0$
0*
0)
1(
#6150000
1$
#6200000
0$
1*
#6250000
1$
#6300000
0$
0*
1)
#6350000
1$
#6400000
0"
0!
0$
1*
