Práctica/tp2ej3/C/TresC.v
module TresC (
    input wire a,
    input wire b,
    input wire c,
    input wire d,
    output wire x
);
    
assign x = (a | b | ~c | ~d) & (a | ~b | c | ~d) & (a | ~b | ~c | d) & (~a | ~b | c | d) & (~a | b | c | ~d) & (~a | b | ~c | d);

endmodule

Práctica/Guía 2/tp2ej3/C/TresC_tb.v
`define DUMPSTR(x) `"x.vcd`"
`timescale 100 ns / 10 ns //Define la unidad de tiempo

module TresC_tb();
    
    parameter DURATION = 10;
    reg clk = 0;
    always #0.5 clk = ~clk;

    reg test_a, test_b, test_c, test_d;
    wire test_x;

    TresC UUT_TresC(
        .a(test_a),
        .b(test_b),
        .c(test_c),
        .d(test_d),
        .x(test_x)
        
    );

    initial begin
        
        $dumpfile(`DUMPSTR(`VCD_OUTPUT));
        $dumpvars(0, TresC_tb);

        #1
        test_a = 0; test_b = 0; test_c = 0; test_d = 0;
        #1
        test_a = 0; test_b = 0; test_c = 0; test_d = 1;
        #1
        test_a = 0; test_b = 0; test_c = 1; test_d = 0;
        #1
        test_a = 0; test_b = 0; test_c = 1; test_d = 1;
        #1
        test_a = 0; test_b = 1; test_c = 0; test_d = 0;
        #1
        test_a = 0; test_b = 1; test_c = 0; test_d = 1;
        #1
        test_a = 0; test_b = 1; test_c = 1; test_d = 0;
        #1
        test_a = 0; test_b = 1; test_c = 1; test_d = 1;
        #1
        test_a = 1; test_b = 0; test_c = 0; test_d = 0;
        #1
        test_a = 1; test_b = 0; test_c = 0; test_d = 1;
        #1
        test_a = 1; test_b = 0; test_c = 1; test_d = 0;
        #1
        test_a = 1; test_b = 0; test_c = 1; test_d = 1;
        #1
        test_a = 1; test_b = 1; test_c = 0; test_d = 0;
        #1
        test_a = 1; test_b = 1; test_c = 0; test_d = 1;
        #1
        test_a = 1; test_b = 1; test_c = 1; test_d = 0;
        #1
        test_a = 1; test_b = 1; test_c = 1; test_d = 1;


        #(DURATION) $display("Fin de la simulación.");        
        $finish;

    end

endmodule

Práctica/Guía 2/tp2ej3/C/TresC_tb.vcd
$date
	Sat Apr 13 13:52:05 2024
$end
$version
	Icarus Verilog
$end
$timescale
	1ps
$end
$scope module TresC_tb $end
$var wire 1 ! test_x $end
$var parameter 32 " DURATION $end
$var reg 1 # clk $end
$var reg 1 $ test_a $end
$var reg 1 % test_b $end
$var reg 1 & test_c $end
$var reg 1 ' test_d $end
$scope module UUT_TresC $end
$var wire 1 $ a $end
$var wire 1 % b $end
$var wire 1 & c $end
$var wire 1 ' d $end
$var wire 1 ! x $end
$upscope $end
$upscope $end
$enddefinitions $end
$comment Show the parameter values. $end
$dumpall
b1010 "
$end
#0
$dumpvars
x'
x&
x%
x$
0#
x!
$end
#50000
1#
#100000
1!
0#
0'
0&
0%
0$
#150000
1#
#200000
0#
1'
#250000
1#
#300000
0#
0'
1&
#350000
1#
#400000
0!
0#
1'
#450000
1#
#500000
1!
0#
0'
0&
1%
#550000
1#
#600000
0!
0#
1'
#650000
1#
#700000
0#
0'
1&
#750000
1#
#800000
1!
0#
1'
#850000
1#
#900000
1!
0#
0'
0&
0%
1$
#950000
1#
#1000000
0!
0#
1'
#1050000
1#
#1100000
0#
0'
1&
#1150000
1#
#1200000
1!
0#
1'
#1250000
1#
#1300000
0!
0#
0'
0&
1%
#1350000
1#
#1400000
1!
0#
1'
#1450000
1#
#1500000
0#
0'
1&
#1550000
1#
#1600000
0#
1'
