Práctica/tp2ej10/tp2ej10.v
module tp2ej10 (
    input wire a,
    input wire b,
    input wire c,
    input wire d,
    input wire e,
    output wire p,
    output wire x,
    output wire t
);
    
assign p = (~a & c & ~d & e) | (~a & ~b & ~c & d) | (~a & ~c & d & e) | (a & ~b & ~c & e) | (~b & d & e) | (a & b & c & e);
assign x = ~e;
assign t = (~a & ~b & ~c & ~d & ~e) | (~a & ~b & ~c & d & e) | (~a & ~b & c & d & ~e) | (~a & b & c & ~d & ~e) | (~a & b & c & d & e) | (~a & b & ~c & ~d & e) | (a & ~b & ~c & d & ~e) | (a & ~b & c & ~d & e) | (a & b & ~c & ~d & ~e) | (a & b & c & d & ~e) | (a & b & ~c & d & e);

endmodule

Práctica/tp2ej10/tp2ej10_tb.v
`define DUMPSTR(x) `"x.vcd`"
`timescale 100 ns / 10 ns //Define la unidad de tiempo

module tp2ej10_tb();
    
    parameter DURATION = 10;
    reg clk = 0;
    always #0.5 clk = ~clk;

    reg test_a, test_b, test_c, test_d, test_e;
    wire test_p, test_x, test_t;

    tp2ej10 UUT_tp2ej10(
        .a(test_a),
        .b(test_b),
        .c(test_c),
        .d(test_d),
        .e(test_e),
        .p(test_p),
        .x(test_x),
        .t(test_t)
        
    );

    initial begin
        
        $dumpfile(`DUMPSTR(`VCD_OUTPUT));
        $dumpvars(0, tp2ej10_tb);

        #1
        test_a = 0; test_b = 0; test_c = 0; test_d = 0; test_e = 0;
        #1
        test_a = 0; test_b = 0; test_c = 0; test_d = 0; test_e = 1;
        #1
        test_a = 0; test_b = 0; test_c = 0; test_d = 1; test_e = 0;
        #1
        test_a = 0; test_b = 0; test_c = 0; test_d = 1; test_e = 1;
        #1
        test_a = 0; test_b = 0; test_c = 1; test_d = 0; test_e = 0;
        #1
        test_a = 0; test_b = 0; test_c = 1; test_d = 0; test_e = 1;
        #1
        test_a = 0; test_b = 0; test_c = 1; test_d = 1; test_e = 0;
        #1
        test_a = 0; test_b = 0; test_c = 1; test_d = 1; test_e = 1;
        #1
        test_a = 0; test_b = 1; test_c = 0; test_d = 0; test_e = 0;
        #1
        test_a = 0; test_b = 1; test_c = 0; test_d = 0; test_e = 1;
        #1
        test_a = 0; test_b = 1; test_c = 0; test_d = 1; test_e = 0;
        #1
        test_a = 0; test_b = 1; test_c = 0; test_d = 1; test_e = 1;
        #1
        test_a = 0; test_b = 1; test_c = 1; test_d = 0; test_e = 0;
        #1
        test_a = 0; test_b = 1; test_c = 1; test_d = 0; test_e = 1;
        #1
        test_a = 0; test_b = 1; test_c = 1; test_d = 1; test_e = 0;
        #1
        test_a = 0; test_b = 1; test_c = 1; test_d = 1; test_e = 1;
        #1
        test_a = 1; test_b = 0; test_c = 0; test_d = 0; test_e = 0;
        #1
        test_a = 1; test_b = 0; test_c = 0; test_d = 0; test_e = 1;
        #1
        test_a = 1; test_b = 0; test_c = 0; test_d = 1; test_e = 0;
        #1
        test_a = 1; test_b = 0; test_c = 0; test_d = 1; test_e = 1;
        #1
        test_a = 1; test_b = 0; test_c = 1; test_d = 0; test_e = 0;
        #1
        test_a = 1; test_b = 0; test_c = 1; test_d = 0; test_e = 1;
        #1
        test_a = 1; test_b = 0; test_c = 1; test_d = 1; test_e = 0;
        #1
        test_a = 1; test_b = 0; test_c = 1; test_d = 1; test_e = 1;
        #1
        test_a = 1; test_b = 1; test_c = 0; test_d = 0; test_e = 0;
        #1
        test_a = 1; test_b = 1; test_c = 0; test_d = 0; test_e = 1;
        #1
        test_a = 1; test_b = 1; test_c = 0; test_d = 1; test_e = 0;
        #1
        test_a = 1; test_b = 1; test_c = 0; test_d = 1; test_e = 1;
        #1
        test_a = 1; test_b = 1; test_c = 1; test_d = 0; test_e = 0;
        #1
        test_a = 1; test_b = 1; test_c = 1; test_d = 0; test_e = 1;
        #1
        test_a = 1; test_b = 1; test_c = 1; test_d = 1; test_e = 0;
        #1
        test_a = 1; test_b = 1; test_c = 1; test_d = 1; test_e = 1;

        #(DURATION) $display("Fin de la simulación.");        
        $finish;

    end

endmodule

Práctica/Guía 2/tp2ej10/tp2ej10_tb.vcd
$date
	Sat Apr 13 20:52:49 2024
$end
$version
	Icarus Verilog
$end
$timescale
	1ps
$end
$scope module tp2ej10_tb $end
$var wire 1 ! test_x $end
$var wire 1 " test_t $end
$var wire 1 # test_p $end
$var parameter 32 $ DURATION $end
$var reg 1 % clk $end
$var reg 1 & test_a $end
$var reg 1 ' test_b $end
$var reg 1 ( test_c $end
$var reg 1 ) test_d $end
$var reg 1 * test_e $end
$scope module UUT_tp2ej10 $end
$var wire 1 & a $end
$var wire 1 ' b $end
$var wire 1 ( c $end
$var wire 1 ) d $end
$var wire 1 * e $end
$var wire 1 # p $end
$var wire 1 " t $end
$var wire 1 ! x $end
$upscope $end
$upscope $end
$enddefinitions $end
$comment Show the parameter values. $end
$dumpall
b1010 $
$end
#0
$dumpvars
x*
x)
x(
x'
x&
0%
x#
x"
x!
$end
#50000
1%
#100000
1"
0#
1!
0%
0*
0)
0(
0'
0&
#150000
1%
#200000
0"
0!
0%
1*
#250000
1%
#300000
1#
1!
0%
0*
1)
#350000
1%
#400000
1"
0!
0%
1*
#450000
1%
#500000
0"
0#
1!
0%
0*
0)
1(
#550000
1%
#600000
1#
0!
0%
1*
#650000
1%
#700000
1"
0#
1!
0%
0*
1)
#750000
1%
#800000
0"
1#
0!
0%
1*
#850000
1%
#900000
0#
1!
0%
0*
0)
0(
1'
#950000
1%
#1000000
1"
0!
0%
1*
#1050000
1%
#1100000
0"
1!
0%
0*
1)
#1150000
1%
#1200000
1#
0!
0%
1*
#1250000
1%
#1300000
1"
0#
1!
0%
0*
0)
1(
#1350000
1%
#1400000
0"
1#
0!
0%
1*
#1450000
1%
#1500000
0#
1!
0%
0*
1)
#1550000
1%
#1600000
1"
0!
0%
1*
#1650000
1%
#1700000
0"
1!
0%
0*
0)
0(
0'
1&
#1750000
1%
#1800000
1#
0!
0%
1*
#1850000
1%
#1900000
1"
0#
1!
0%
0*
1)
#1950000
1%
#2000000
0"
1#
0!
0%
1*
#2050000
1%
#2100000
0#
1!
0%
0*
0)
1(
#2150000
1%
#2200000
1"
0!
0%
1*
#2250000
1%
#2300000
0"
1!
0%
0*
1)
#2350000
1%
#2400000
1#
0!
0%
1*
#2450000
1%
#2500000
1"
0#
1!
0%
0*
0)
0(
1'
#2550000
1%
#2600000
0"
0!
0%
1*
#2650000
1%
#2700000
1!
0%
0*
1)
#2750000
1%
#2800000
1"
0!
0%
1*
#2850000
1%
#2900000
0"
1!
0%
0*
0)
1(
#2950000
1%
#3000000
1#
0!
0%
1*
#3050000
1%
#3100000
1"
0#
1!
0%
0*
1)
#3150000
1%
#3200000
0"
1#
0!
0%
1*
