Práctica/Guía 5/Verilog/tp5ej4/b/d_syncrst.v
module d_syncrst(
    input clk,d,clr,
    output reg q
);

always @(posedge clk) begin
    
    q=d;

end

always @(posedge clk & clr) begin
    q=0;
end


endmodule

Práctica/Guía 5/Verilog/tp5ej4/b/d_syncrst_tb.v
`default_nettype none
`define DUMPSTR(x) `"x.vcd`"
`timescale 100 ns / 10 ns //Define la unidad de tiempo

module d_syncrst_tb();
    
    parameter DURATION = 10;

    reg clk, d, clr;
    wire q;

    d_syncrst UUT(
        .clk(clk),
        .d(d),
        .clr(clr),
        .q(q)
        
    );

    always #0.5 clk = !clk;
    always #1.5 d = d + 1;


    initial begin
        
        $dumpfile(`DUMPSTR(`VCD_OUTPUT));
        $dumpvars(0, d_syncrst_tb);
        clk = 0;
        d = 0;
        clr = 0;
        #5 clr=1;
        #(DURATION) $display("Fin de la simulación.");  


        $finish;

    end

endmodule

Práctica/Guía 5/Verilog/tp5ej4/b/d_syncrst_tb.vcd
$date
	Wed May 22 15:05:10 2024
$end
$version
	Icarus Verilog
$end
$timescale
	1ps
$end
$scope module d_syncrst_tb $end
$var wire 1 ! q $end
$var parameter 32 " DURATION $end
$var reg 1 # clk $end
$var reg 1 $ clr $end
$var reg 1 % d $end
$scope module UUT $end
$var wire 1 # clk $end
$var wire 1 $ clr $end
$var wire 1 % d $end
$var reg 1 ! q $end
$upscope $end
$upscope $end
$enddefinitions $end
$comment Show the parameter values. $end
$dumpall
b1010 "
$end
#0
$dumpvars
0%
0$
0#
x!
$end
#50000
0!
1#
#100000
0#
#150000
1!
1#
1%
#200000
0#
#250000
1#
#300000
0#
0%
#350000
0!
1#
#400000
0#
#450000
1!
1#
1%
#500000
0#
1$
#550000
0!
1#
#600000
0#
0%
#650000
1#
#700000
0#
#750000
0!
1#
1%
#800000
0#
#850000
0!
1#
#900000
0#
0%
#950000
1#
#1000000
0#
#1050000
0!
1#
1%
#1100000
0#
#1150000
0!
1#
#1200000
0#
0%
#1250000
1#
#1300000
0#
#1350000
0!
1#
1%
#1400000
0#
#1450000
0!
1#
#1500000
0#
0%
