Práctica/Guía 5/Verilog/tp5ej3/t.v
module t (
    input wire clk,
    input wire t,
    input wire rst,
    output reg q
);

always @(posedge clk) begin
    
    case (t)
        1'b0: q=q;
        default: q=~q;
    endcase

end

always @(posedge rst) begin
    q=0;
end


endmodule

Práctica/Guía 5/Verilog/tp5ej3/t_tb.v
`default_nettype none
`define DUMPSTR(x) `"x.vcd`"
`timescale 100 ns / 10 ns //Define la unidad de tiempo

module t_tb();
    
    parameter DURATION = 10;

    reg clk, t, rst;
    wire q;

    t UUT(
        .clk(clk),
        .t(t),
        .rst(rst),
        .q(q)
        
    );

    always #0.5 clk = !clk;
    always #5 t = t + 1;


    initial begin
        
        $dumpfile(`DUMPSTR(`VCD_OUTPUT));
        $dumpvars(0, t_tb);
        rst = 1;
        clk = 0;
        t = 0;
        #0.5 rst = 0;

        #(DURATION) $display("Fin de la simulación.");  
 
        $finish;

    end

endmodule

Práctica/Guía 5/Verilog/tp5ej3/t_tb.vcd
$date
	Wed May 22 14:06:20 2024
$end
$version
	Icarus Verilog
$end
$timescale
	1ps
$end
$scope module t_tb $end
$var wire 1 ! q $end
$var parameter 32 " DURATION $end
$var reg 1 # clk $end
$var reg 1 $ rst $end
$var reg 1 % t $end
$scope module UUT $end
$var wire 1 # clk $end
$var wire 1 $ rst $end
$var wire 1 % t $end
$var reg 1 ! q $end
$upscope $end
$upscope $end
$enddefinitions $end
$comment Show the parameter values. $end
$dumpall
b1010 "
$end
#0
$dumpvars
0%
1$
0#
0!
$end
#50000
0$
1#
#100000
0#
#150000
1#
#200000
0#
#250000
1#
#300000
0#
#350000
1#
#400000
0#
#450000
1#
#500000
0#
1%
#550000
1!
1#
#600000
0#
#650000
0!
1#
#700000
0#
#750000
1!
1#
#800000
0#
#850000
0!
1#
#900000
0#
#950000
1!
1#
#1000000
0#
0%
