Práctica/Guía 5/Verilog/tp5ej7/d.v
module d(
    input clk,d,
    output reg q
);

always @(posedge clk) begin
    
    q=d;

end

endmodule

Práctica/Guía 5/Verilog/tp5ej7/top.v
// `include "d.v"

module top (
    input wire clk,
    input wire data_in,
    output wire [3:0] data_out
);


d ffd_0 (
    .clk(clk),
    .d(data_in),
    .q(data_out[0])
);

d ffd_1 (
    .clk(clk),
    .d(data_out[0]),
    .q(data_out[1])
);

d ffd_2 (
    .clk(clk),
    .d(data_out[1]),
    .q(data_out[2])
);

d ffd_3 (
    .clk(clk),
    .d(data_out[2]),
    .q(data_out[3])
);




endmodule

Práctica/Guía 5/Verilog/tp5ej7/top_tb.v
`default_nettype none
`define DUMPSTR(x) `"x.vcd`"
`timescale 100 ns/ 10 ns

module top_tb();

parameter DURATION = 10;


reg clk;
reg data_in;
wire [3:0] data_out;

top UTTtop(
    .data_in(data_in),
    .clk(clk),
    .data_out(data_out)
);

always #0.5 clk = !clk;

initial begin
    $dumpfile(`DUMPSTR(`VCD_OUTPUT));
    $dumpvars(0, top_tb);
    
    clk = 0;
    #0.5 data_in = 1;
    #1 data_in = 0;
    #1 data_in = 1;
    #2 data_in = 0;


    #(DURATION) $display("Fin de la simulacion");
    $finish;

end

endmodule

Práctica/Guía 5/Verilog/tp5ej7/top_tb.vcd
$date
	Thu May 23 20:13:47 2024
$end
$version
	Icarus Verilog
$end
$timescale
	1ps
$end
$scope module top_tb $end
$var wire 4 ! data_out [3:0] $end
$var parameter 32 " DURATION $end
$var reg 1 # clk $end
$var reg 1 $ data_in $end
$scope module UTTtop $end
$var wire 1 # clk $end
$var wire 1 $ data_in $end
$var wire 4 % data_out [3:0] $end
$scope module ffd_0 $end
$var wire 1 # clk $end
$var wire 1 $ d $end
$var reg 1 & q $end
$upscope $end
$scope module ffd_1 $end
$var wire 1 # clk $end
$var wire 1 ' d $end
$var reg 1 ( q $end
$upscope $end
$scope module ffd_2 $end
$var wire 1 # clk $end
$var wire 1 ) d $end
$var reg 1 * q $end
$upscope $end
$scope module ffd_3 $end
$var wire 1 # clk $end
$var wire 1 + d $end
$var reg 1 , q $end
$upscope $end
$upscope $end
$upscope $end
$enddefinitions $end
$comment Show the parameter values. $end
$dumpall
b1010 "
$end
#0
$dumpvars
x,
x+
x*
x)
x(
x'
x&
bx %
x$
0#
bx !
$end
#50000
1'
bx1 !
bx1 %
1&
1$
1#
#100000
0#
#150000
1)
0'
1(
bx10 !
bx10 %
0&
1#
0$
#200000
0#
#250000
1'
0)
1+
1&
0(
bx101 !
bx101 %
1*
1#
1$
#300000
0#
#350000
0+
1)
1,
0*
b1011 !
b1011 %
1(
1#
#400000
0#
#450000
0'
1+
0&
1*
b110 !
b110 %
0,
1#
0$
#500000
0#
#550000
0)
1,
b1100 !
b1100 %
0(
1#
#600000
0#
#650000
0+
b1000 !
b1000 %
0*
1#
#700000
0#
#750000
b0 !
b0 %
0,
1#
