Práctica/Guía 2/tp2ej9/A/NueveA.v
module NueveA (
    input wire a,
    input wire b,
    input wire c,
    output wire x,
    output wire y
);
    
assign x = (a & ~b & c) | (~a & b & ~c) | (a & b & c);
assign y = (a & c) | (~a & b & ~c);

endmodule

Práctica/tp2ej9/A/NueveA_tb.v
`define DUMPSTR(x) `"x.vcd`"
`timescale 100 ns / 10 ns //Define la unidad de tiempo

module NueveA_tb();
    
    parameter DURATION = 10;
    reg clk = 0;
    always #0.5 clk = ~clk;

    reg test_a, test_b, test_c;
    wire test_x, test_y;

    NueveA UUT_NueveA(
        .a(test_a),
        .b(test_b),
        .c(test_c),
        .x(test_x),
        .y(test_y)
    );

    initial begin
        
        $dumpfile(`DUMPSTR(`VCD_OUTPUT));
        $dumpvars(0, NueveA_tb);

        #1
        test_a = 0; test_b = 0; test_c = 0;
        #1
        test_a = 0; test_b = 0; test_c = 1;
        #1
        test_a = 0; test_b = 1; test_c = 0;
        #1
        test_a = 0; test_b = 1; test_c = 1;
        #1
        test_a = 1; test_b = 0; test_c = 0;
        #1
        test_a = 1; test_b = 0; test_c = 1;
        #1
        test_a = 1; test_b = 1; test_c = 0;
        #1
        test_a = 1; test_b = 1; test_c = 1;



        #(DURATION) $display("Fin de la simulación.");        
        $finish;

    end

endmodule

Práctica/tp2ej9/A/NueveA_tb.vcd
$date
	Sat Apr 13 18:39:50 2024
$end
$version
	Icarus Verilog
$end
$timescale
	1ps
$end
$scope module NueveA_tb $end
$var wire 1 ! test_y $end
$var wire 1 " test_x $end
$var parameter 32 # DURATION $end
$var reg 1 $ clk $end
$var reg 1 % test_a $end
$var reg 1 & test_b $end
$var reg 1 ' test_c $end
$scope module UUT_NueveA $end
$var wire 1 % a $end
$var wire 1 & b $end
$var wire 1 ' c $end
$var wire 1 " x $end
$var wire 1 ! y $end
$upscope $end
$upscope $end
$enddefinitions $end
$comment Show the parameter values. $end
$dumpall
b1010 #
$end
#0
$dumpvars
x'
x&
x%
0$
x"
x!
$end
#50000
1$
#100000
0"
0!
0$
0'
0&
0%
#150000
1$
#200000
0$
1'
#250000
1$
#300000
1"
1!
0$
0'
1&
#350000
1$
#400000
0"
0!
0$
1'
#450000
1$
#500000
0$
0'
0&
1%
#550000
1$
#600000
1"
1!
0$
1'
#650000
1$
#700000
0"
0!
0$
0'
1&
#750000
1$
#800000
1"
1!
0$
1'
