Práctica/Guía 2/tp2ej2/xor_1_bit.v
module xor_1_bit (
    input wire a,
    input wire b,
    input wire c,
    output wire x
);

assign x = ~(a | b | c);
    
endmodule

Práctica/Guía 2/tp2ej2/xor_1_bit_tb.v
`define DUMPSTR(x) `"x.vcd`"
`timescale 100 ns / 10 ns //Define la unidad de tiempo

module xor_1_bit_tb();
    
    parameter DURATION = 10;
    reg clk = 0;
    always #0.5 clk = ~clk;

    reg test_a, test_b, test_c;
    wire test_x;

    xor_1_bit UUT_xor_1_bit(
        .a(test_a),
        .b(test_b),
        .c(test_c),
        .x(test_x)
        
    );

    initial begin
        
        $dumpfile(`DUMPSTR(`VCD_OUTPUT));
        $dumpvars(0, xor_1_bit_tb);

        #1
        test_a = 0; test_b = 0; test_c = 0;
        #1
        test_a = 1; test_b = 0; test_c = 0;
        #1
        test_a = 1; test_b = 0; test_c = 1;
        #1
        test_a = 1; test_b = 0; test_c = 0;
        #1
        test_a = 1; test_b = 1; test_c = 0;
        #1
        test_a = 1; test_b = 1; test_c = 1;
        #1
        test_a = 1; test_b = 1; test_c = 0;
        #1
        test_a = 0; test_b = 1; test_c = 0;
        #1
        test_a = 0; test_b = 0; test_c = 0;
        #1
        test_a = 0; test_b = 0; test_c = 1;
        #1
        test_a = 0; test_b = 0; test_c = 0;
        #1
        test_a = 1; test_b = 0; test_c = 0;
        #1
        test_a = 1; test_b = 1; test_c = 0;
        #1
        test_a = 1; test_b = 1; test_c = 1;
        #1
        test_a = 1; test_b = 1; test_c = 0;
        #1
        test_a = 0; test_b = 1; test_c = 0;
        #1
        test_a = 0; test_b = 0; test_c = 0;
        #1
        test_a = 0; test_b = 0; test_c = 1;
        #1
        test_a = 0; test_b = 0; test_c = 0;


        #(DURATION) $display("Fin de la simulación.");        
        $finish;

    end

endmodule

Práctica/Guía 2/tp2ej2/xor_1_bit_tb.vcd
$date
	Sat Apr 13 13:48:27 2024
$end
$version
	Icarus Verilog
$end
$timescale
	1ps
$end
$scope module xor_1_bit_tb $end
$var wire 1 ! test_x $end
$var parameter 32 " DURATION $end
$var reg 1 # clk $end
$var reg 1 $ test_a $end
$var reg 1 % test_b $end
$var reg 1 & test_c $end
$scope module UUT_xor_1_bit $end
$var wire 1 $ a $end
$var wire 1 % b $end
$var wire 1 & c $end
$var wire 1 ! x $end
$upscope $end
$upscope $end
$enddefinitions $end
$comment Show the parameter values. $end
$dumpall
b1010 "
$end
#0
$dumpvars
x&
x%
x$
0#
x!
$end
#50000
1#
#100000
1!
0#
0&
0%
0$
#150000
1#
#200000
0!
0#
1$
#250000
1#
#300000
0#
1&
#350000
1#
#400000
0#
0&
#450000
1#
#500000
0#
1%
#550000
1#
#600000
0#
1&
#650000
1#
#700000
0#
0&
#750000
1#
#800000
0#
0$
#850000
1#
#900000
1!
0#
0%
#950000
1#
#1000000
0!
0#
1&
#1050000
1#
#1100000
1!
0#
0&
#1150000
1#
#1200000
0!
0#
1$
#1250000
1#
#1300000
0#
1%
#1350000
1#
#1400000
0#
1&
#1450000
1#
#1500000
0#
0&
#1550000
1#
#1600000
0#
0$
#1650000
1#
#1700000
1!
0#
0%
#1750000
1#
#1800000
0!
0#
1&
#1850000
1#
#1900000
1!
0#
0&
